radtts/LICENSE
radtts/README.md
radtts/alignment.py
radtts/attribute_prediction_model.py
radtts/audio_processing.py
radtts/autoregressive_flow.py
radtts/common.py
radtts/data.py
radtts/distributed.py
radtts/hifigan_denoiser.py
radtts/hifigan_env.py
radtts/hifigan_models.py
radtts/hifigan_utils.py
radtts/inference.py
radtts/inference_voice_conversion.py
radtts/loss.py
radtts/partialconv1d.py
radtts/plotting_utils.py
radtts/radam.py
radtts/radtts.py
radtts/splines.py
radtts/train.py
radtts/transformer.py
radtts/tts_text_processing/LICENSE
radtts/tts_text_processing/abbreviations.py
radtts/tts_text_processing/acronyms.py
radtts/tts_text_processing/cleaners.py
radtts/tts_text_processing/cmudict-0.7b
radtts/tts_text_processing/cmudict.py
radtts/tts_text_processing/datestime.py
radtts/tts_text_processing/grapheme_dictionary.py
radtts/tts_text_processing/heteronyms
radtts/tts_text_processing/letters_and_numbers.py
radtts/tts_text_processing/numerical.py
radtts/tts_text_processing/symbols.py
radtts/tts_text_processing/text_processing.py
radtts-22.12.29.dist-info/entry_points.txt
radtts-22.12.29.dist-info/METADATA
radtts-22.12.29.dist-info/WHEEL
radtts-22.12.29.dist-info/RECORD
