Metadata-Version: 2.1
Name: radtts
Version: 22.12.29
Summary: RADTTS library
Home-page: http://github.com/8tm/radtts
Author: Tadeusz Miszczyk
Author-email: 42252259+8tm@users.noreply.github.com
Requires-Python: >=3.8,<4.0
Classifier: Environment :: Console
Classifier: Intended Audience :: Developers
Classifier: Operating System :: Unix
Classifier: Programming Language :: Python :: 3
Classifier: Programming Language :: Python :: 3.8
Classifier: Programming Language :: Python :: 3.9
Classifier: Programming Language :: Python :: 3.10
Classifier: Programming Language :: Python :: 3.11
Classifier: Programming Language :: Python :: 3 :: Only
Classifier: Programming Language :: Python :: 3.10
Classifier: Programming Language :: Python :: 3.11
Classifier: Programming Language :: Python :: 3.8
Classifier: Programming Language :: Python :: 3.9
Requires-Dist: Pillow (>=9.3.0,<10.0.0)
Requires-Dist: Unidecode (>=1.3.6,<2.0.0)
Requires-Dist: audioread (>=3.0.0,<4.0.0)
Requires-Dist: inflect (>=6.0.2,<7.0.0)
Requires-Dist: jupyter (>=1.0.0,<2.0.0)
Requires-Dist: librosa (>=0.9.2,<0.10.0)
Requires-Dist: lmdb (>=1.4.0,<2.0.0)
Requires-Dist: matplotlib (>=3.6.2,<4.0.0)
Requires-Dist: natsort (>=8.2.0,<9.0.0)
Requires-Dist: pandas (>=1.5.2,<2.0.0)
Requires-Dist: peakutils (>=1.3.4,<2.0.0)
Requires-Dist: soundfile (>=0.11.0,<0.12.0)
Requires-Dist: sox (>=1.4.1,<2.0.0)
Requires-Dist: srt (>=3.5.2,<4.0.0)
Requires-Dist: tgt (>=1.4.4,<2.0.0)
Requires-Dist: webrtcvad (>=2.0.10,<3.0.0)
Project-URL: Documentation, https://test.pypi.org/project/radtts
Project-URL: Repository, http://github.com/8tm/radtts
